kostyl/__init__.py
kostyl/ml/__init__.py
kostyl/ml/clearml/__init__.py
kostyl/ml/clearml/dataset_utils.py
kostyl/ml/clearml/logging_utils.py
kostyl/ml/clearml/pulling_utils.py
kostyl/ml/configs/__init__.py
kostyl/ml/configs/base_model.py
kostyl/ml/configs/hyperparams.py
kostyl/ml/configs/training_settings.py
kostyl/ml/data_processing_utils.py
kostyl/ml/dist_utils.py
kostyl/ml/lightning/__init__.py
kostyl/ml/lightning/callbacks/__init__.py
kostyl/ml/lightning/callbacks/checkpoint.py
kostyl/ml/lightning/callbacks/early_stopping.py
kostyl/ml/lightning/extensions/__init__.py
kostyl/ml/lightning/extensions/custom_module.py
kostyl/ml/lightning/extensions/pretrained_model.py
kostyl/ml/lightning/loggers/__init__.py
kostyl/ml/lightning/loggers/tb_logger.py
kostyl/ml/lightning/training_utils.py
kostyl/ml/metrics_formatting.py
kostyl/ml/params_groups.py
kostyl/ml/registry_uploader.py
kostyl/ml/schedulers/__init__.py
kostyl/ml/schedulers/base.py
kostyl/ml/schedulers/composite.py
kostyl/ml/schedulers/cosine.py
kostyl/ml/schedulers/linear.py
kostyl/utils/__init__.py
kostyl/utils/dict_manipulations.py
kostyl/utils/fs.py
kostyl/utils/logging.py
kostyl_toolkit-0.1.35.dist-info/WHEEL
kostyl_toolkit-0.1.35.dist-info/METADATA
kostyl_toolkit-0.1.35.dist-info/RECORD
