Metadata-Version: 2.3
Name: kostyl-toolkit
Version: 0.1.35
Summary: Kickass Orchestration System for Training, Yielding & Logging 
Requires-Dist: case-converter>=1.2.0
Requires-Dist: loguru>=0.7.3
Requires-Dist: case-converter>=1.2.0 ; extra == 'ml-core'
Requires-Dist: clearml[s3]>=2.0.2 ; extra == 'ml-core'
Requires-Dist: lightning>=2.5.6 ; extra == 'ml-core'
Requires-Dist: pydantic>=2.12.4 ; extra == 'ml-core'
Requires-Dist: torch>=2.9.1 ; extra == 'ml-core'
Requires-Dist: transformers>=4.57.1 ; extra == 'ml-core'
Requires-Python: >=3.12
Provides-Extra: ml-core
